datalink/__init__.py
datalink/errors.py
datalink/links.py
datalink/stores.py
datalink/utils.py
datalink-0.1.3.dist-info/LICENSE
datalink-0.1.3.dist-info/METADATA
datalink-0.1.3.dist-info/WHEEL
datalink-0.1.3.dist-info/top_level.txt
datalink-0.1.3.dist-info/RECORD
