Metadata-Version: 2.1
Name: datalink
Version: 0.1.3
Summary: Create simple interfaces to SQL that make working with data as simple as working with dictionaries.
Home-page: https://github.com/hypernormalisation/datalink
Author: Stephen Ogilvy
Author-email: sogilvy@protonmail.com
License: UNKNOWN
Project-URL: Bug Reports, https://github.com/hypernormalisation/datalink/issues
Project-URL: Source, https://github.com/hypernormalisation/datalink
Keywords: development database sql pandas
Platform: UNKNOWN
Classifier: Development Status :: 4 - Beta
Classifier: Intended Audience :: Developers
Classifier: Topic :: Database :: Front-Ends
Classifier: License :: OSI Approved :: GNU General Public License v3 or later (GPLv3+)
Classifier: Programming Language :: Python :: 3.6
Classifier: Programming Language :: Python :: 3.7
Classifier: Programming Language :: Python :: 3.8
Requires-Python: >=3.6
Requires-Dist: sqlalchemy
Requires-Dist: dataset
Requires-Dist: sqlalchemy-utils
Requires-Dist: traits (==5.2.0)
Requires-Dist: pandas
